apiposture/__init__.py
apiposture/__main__.py
apiposture/cli/__init__.py
apiposture/cli/app.py
apiposture/cli/license.py
apiposture/cli/scan.py
apiposture/core/__init__.py
apiposture/core/analysis/__init__.py
apiposture/core/analysis/project_analyzer.py
apiposture/core/analysis/source_loader.py
apiposture/core/authorization/__init__.py
apiposture/core/authorization/django_auth.py
apiposture/core/authorization/extractor.py
apiposture/core/authorization/fastapi_auth.py
apiposture/core/authorization/flask_auth.py
apiposture/core/classification/__init__.py
apiposture/core/classification/classifier.py
apiposture/core/configuration/__init__.py
apiposture/core/configuration/loader.py
apiposture/core/discovery/__init__.py
apiposture/core/discovery/base.py
apiposture/core/discovery/django_drf.py
apiposture/core/discovery/fastapi.py
apiposture/core/discovery/flask.py
apiposture/core/licensing/__init__.py
apiposture/core/licensing/context.py
apiposture/core/licensing/manager.py
apiposture/core/models/__init__.py
apiposture/core/models/authorization.py
apiposture/core/models/endpoint.py
apiposture/core/models/enums.py
apiposture/core/models/finding.py
apiposture/core/models/scan_result.py
apiposture/output/__init__.py
apiposture/output/base.py
apiposture/output/json_output.py
apiposture/output/markdown.py
apiposture/output/terminal.py
apiposture/rules/__init__.py
apiposture/rules/base.py
apiposture/rules/engine.py
apiposture/rules/consistency/__init__.py
apiposture/rules/consistency/ap003_auth_conflict.py
apiposture/rules/consistency/ap004_missing_auth_writes.py
apiposture/rules/exposure/__init__.py
apiposture/rules/exposure/ap001_public_without_intent.py
apiposture/rules/exposure/ap002_anonymous_on_write.py
apiposture/rules/privilege/__init__.py
apiposture/rules/privilege/ap005_excessive_roles.py
apiposture/rules/privilege/ap006_weak_role_naming.py
apiposture/rules/surface/__init__.py
apiposture/rules/surface/ap007_sensitive_keywords.py
apiposture-0.1.0.dist-info/METADATA
apiposture-0.1.0.dist-info/WHEEL
apiposture-0.1.0.dist-info/entry_points.txt
apiposture-0.1.0.dist-info/licenses/LICENSE
apiposture-0.1.0.dist-info/RECORD
