Metadata-Version: 2.4
Name: apiposture
Version: 0.1.0
Summary: A CLI security inspection tool for Python API frameworks
Project-URL: Homepage, https://github.com/apiposture/apiposture-python
Project-URL: Documentation, https://github.com/apiposture/apiposture-python#readme
Project-URL: Repository, https://github.com/apiposture/apiposture-python
Project-URL: Issues, https://github.com/apiposture/apiposture-python/issues
Author: ApiPosture Team
License-Expression: MIT
License-File: LICENSE
Keywords: api,authorization,django,fastapi,flask,security,static-analysis
Classifier: Development Status :: 4 - Beta
Classifier: Environment :: Console
Classifier: Intended Audience :: Developers
Classifier: License :: OSI Approved :: MIT License
Classifier: Operating System :: OS Independent
Classifier: Programming Language :: Python :: 3
Classifier: Programming Language :: Python :: 3.10
Classifier: Programming Language :: Python :: 3.11
Classifier: Programming Language :: Python :: 3.12
Classifier: Topic :: Security
Classifier: Topic :: Software Development :: Quality Assurance
Requires-Python: >=3.10
Requires-Dist: pyyaml>=6.0
Requires-Dist: rich>=13.0.0
Requires-Dist: typer>=0.9.0
Provides-Extra: dev
Requires-Dist: mypy>=1.0.0; extra == 'dev'
Requires-Dist: pytest-cov>=4.0.0; extra == 'dev'
Requires-Dist: pytest>=7.0.0; extra == 'dev'
Requires-Dist: ruff>=0.1.0; extra == 'dev'
